bb_mcp/__init__.py
bb_mcp/__main__.py
bb_mcp/bb_mcp.py
bb_mcp/cache.py
bb_mcp/client.py
bb_mcp/config.py
bb_mcp/models.py
bb_mcp/service.py
mcp_server_bb-0.2.15.dist-info/METADATA
mcp_server_bb-0.2.15.dist-info/WHEEL
mcp_server_bb-0.2.15.dist-info/entry_points.txt
mcp_server_bb-0.2.15.dist-info/RECORD
