Metadata-Version: 2.4
Name: mcp-server-bb
Version: 0.2.15
Summary: A mcp for bb
Author-email: Ming Wen <wen123090613@gmail.com>
Keywords: BB,CUHKSZ,MCP
Classifier: License :: OSI Approved :: MIT License
Classifier: Operating System :: OS Independent
Classifier: Programming Language :: Python :: 3
Requires-Python: >=3.11
Requires-Dist: httpx==0.27.2
Requires-Dist: mcp[cli]>=1.9.2
Requires-Dist: pydantic>=2.7.0
Requires-Dist: python-dotenv>=1.0.1
Requires-Dist: selectolax>=0.3.17
